.gitignore
.travis.yml
LICENSE
MANIFEST.in
README.md
requirements.txt
run.py
setup.py
multiflexxlib/__init__.py
multiflexxlib/_version.py
multiflexxlib/mftools.py
multiflexxlib/plotting.py
multiflexxlib/ub.py
multiflexxlib.egg-info/PKG-INFO
multiflexxlib.egg-info/SOURCES.txt
multiflexxlib.egg-info/dependency_links.txt
multiflexxlib.egg-info/not-zip-safe
multiflexxlib.egg-info/requires.txt
multiflexxlib.egg-info/top_level.txt
multiflexxlib/res/alive.csv
multiflexxlib/res/int_corr.csv
multiflexxlib/res/weights.csv
sampledata/MnF2/058773
sampledata/MnF2/058774
sampledata/MnF2/058775
sampledata/MnF2/058776
sampledata/MnF2/058777
sampledata/MnF2/058778
sampledata/MnF2/058779
sampledata/MnF2/058780
sampledata/MnF2/1/058773
sampledata/MnF2/1/058774
sampledata/MnF2/12/058773
sampledata/MnF2/12/058774
sampledata/MnF2/12/058775
sampledata/MnF2/12/058776
sampledata/MnF2/2/058775
sampledata/MnF2/2/058776
sampledata/MnF2/3/058777
sampledata/MnF2/3/058778
sampledata/MnF2/34/058777
sampledata/MnF2/34/058778
sampledata/MnF2/34/058779
sampledata/MnF2/34/058780
sampledata/MnF2/4/058779
sampledata/MnF2/4/058780